fiit.py
fiit-1.0.2.dist-info/DESCRIPTION.rst
fiit-1.0.2.dist-info/METADATA
fiit-1.0.2.dist-info/RECORD
fiit-1.0.2.dist-info/WHEEL
fiit-1.0.2.dist-info/entry_points.txt
fiit-1.0.2.dist-info/metadata.json
fiit-1.0.2.dist-info/top_level.txt
