Metadata-Version: 2.0
Name: fiit
Version: 1.0.2
Summary: Line fitter for FIZ151
Home-page: https://github.com/nsgonultas/fiit
Author: Enes Gönültaş
Author-email: nsgonultas@gmail.com
License: UNKNOWN
Keywords: fiz151 line fit
Platform: UNKNOWN
